prometheus_client_python_speedups-0.1.0.dist-info/METADATA
prometheus_client_python_speedups-0.1.0.dist-info/WHEEL
prometheus_client_python_speedups-0.1.0.dist-info/licenses/LICENSE
prometheus_client_python_speedups/__init__.py
prometheus_client_python_speedups/prometheus_client_python_speedups.pypy39-pp73-s390x-linux-gnu.so
prometheus_client_python_speedups-0.1.0.dist-info/RECORD
